datadbs/__init__.py
datadbs/amqp.py
datadbs/bnc.py
datadbs/echo.py
datadbs/general.py
datadbs/geojson.py
datadbs/gsof.py
datadbs/plaintext.py
datadbs/redis.py
datadbs/rethinkdb.py
datadbs/websocket.py
datadbs-0.1.1.dist-info/METADATA
datadbs-0.1.1.dist-info/WHEEL
datadbs-0.1.1.dist-info/top_level.txt
datadbs-0.1.1.dist-info/RECORD
